Metadata-Version: 2.1
Name: gtuworld
Version: 1.0.1
Summary: Download GTU papers within seconds.
Home-page: https://github.com/dhirajberi/gtuworld
Author: Dhiraj Beri
Author-email: dhirajberi.official@gmail.com
License: MIT
Download-URL: https://github.com/dhirajberi/gtuworld/archive/refs/tags/v1.0.1.tar.gz
Keywords: gtu paper download,gtuworld,gtu paper download using python
Platform: UNKNOWN
Classifier: Development Status :: 3 - Alpha
Classifier: Intended Audience :: Developers
Classifier: Topic :: Software Development :: Build Tools
Classifier: License :: OSI Approved :: MIT License
Classifier: Programming Language :: Python :: 3
Classifier: Programming Language :: Python :: 3.4
Classifier: Programming Language :: Python :: 3.5
Classifier: Programming Language :: Python :: 3.6
Classifier: Programming Language :: Python :: 3.7
Classifier: Programming Language :: Python :: 3.8
